[
  {
    "category": "fruits",
    "split_label": "fold_0",
    "split_seed": 0,
    "split_mode": "balanced_exemplar_folds",
    "model_name": "convnext_tiny",
    "pooling": "auto",
    "layer": "layer_0",
    "n_stored": 80,
    "n_probe": 40,
    "chance_accuracy": 1.25,
    "ident_accuracy": 98.75,
    "ident_avg_target_sim": 0.9991338193006808,
    "ident_avg_margin": 0.0026378252895110934,
    "gen_accuracy": 12.5,
    "gen_avg_target_sim": 0.9916162444646677,
    "gen_avg_margin": -0.0046209991160993,
    "gen_avg_retrieved_human_similarity": 0.41050000000000003,
    "gen_avg_human_similarity_regret": 0.38899999999999996,
    "gen_same_concept_accuracy": 17.5,
    "human_rdm_spearman": 0.18964198467740265,
    "exact_accuracy": 100.0,
    "clean_reextract_accuracy": 100.0,
    "exact_avg_target_sim": 1.0000000342716724,
    "clean_reextract_avg_target_sim": 1.0000000342716724
  },
  {
    "category": "fruits",
    "split_label": "fold_0",
    "split_seed": 0,
    "split_mode": "balanced_exemplar_folds",
    "model_name": "convnext_tiny",
    "pooling": "auto",
    "layer": "layer_2",
    "n_stored": 80,
    "n_probe": 40,
    "chance_accuracy": 1.25,
    "ident_accuracy": 100.0,
    "ident_avg_target_sim": 0.9999870173615613,
    "ident_avg_margin": 0.0005071573207679758,
    "gen_accuracy": 15.0,
    "gen_avg_target_sim": 0.9992574020925673,
    "gen_avg_margin": -0.00022946894466177036,
    "gen_avg_retrieved_human_similarity": 0.546194445,
    "gen_avg_human_similarity_regret": 0.25330555499999996,
    "gen_same_concept_accuracy": 37.5,
    "human_rdm_spearman": 0.37771650462440576,
    "exact_accuracy": 100.0,
    "clean_reextract_accuracy": 100.0,
    "exact_avg_target_sim": 1.0000000558783566,
    "clean_reextract_avg_target_sim": 1.0000000558783566
  },
  {
    "category": "fruits",
    "split_label": "fold_0",
    "split_seed": 0,
    "split_mode": "balanced_exemplar_folds",
    "model_name": "convnext_tiny",
    "pooling": "auto",
    "layer": "layer_3",
    "n_stored": 80,
    "n_probe": 40,
    "chance_accuracy": 1.25,
    "ident_accuracy": 100.0,
    "ident_avg_target_sim": 0.9906531703283713,
    "ident_avg_margin": 0.1924897181753464,
    "gen_accuracy": 42.5,
    "gen_avg_target_sim": 0.7354856409279477,
    "gen_avg_margin": -0.041934140171901946,
    "gen_avg_retrieved_human_similarity": 0.7156944450000001,
    "gen_avg_human_similarity_regret": 0.083805555,
    "gen_same_concept_accuracy": 82.5,
    "human_rdm_spearman": 0.2977470615311246,
    "exact_accuracy": 100.0,
    "clean_reextract_accuracy": 100.0,
    "exact_avg_target_sim": 1.000000026076033,
    "clean_reextract_avg_target_sim": 1.000000026076033
  },
  {
    "category": "fruits",
    "split_label": "fold_1",
    "split_seed": 1,
    "split_mode": "balanced_exemplar_folds",
    "model_name": "convnext_tiny",
    "pooling": "auto",
    "layer": "layer_0",
    "n_stored": 80,
    "n_probe": 40,
    "chance_accuracy": 1.25,
    "ident_accuracy": 98.75,
    "ident_avg_target_sim": 0.9991257108297095,
    "ident_avg_margin": 0.002857800626581519,
    "gen_accuracy": 12.5,
    "gen_avg_target_sim": 0.9915476349447495,
    "gen_avg_margin": -0.00475116389488324,
    "gen_avg_retrieved_human_similarity": 0.3664722225,
    "gen_avg_human_similarity_regret": 0.4415833324999999,
    "gen_same_concept_accuracy": 15.0,
    "human_rdm_spearman": 0.18964198467740265,
    "exact_accuracy": 100.0,
    "clean_reextract_accuracy": 100.0,
    "exact_avg_target_sim": 1.0000000402321372,
    "clean_reextract_avg_target_sim": 1.0000000402321372
  },
  {
    "category": "fruits",
    "split_label": "fold_1",
    "split_seed": 1,
    "split_mode": "balanced_exemplar_folds",
    "model_name": "convnext_tiny",
    "pooling": "auto",
    "layer": "layer_2",
    "n_stored": 80,
    "n_probe": 40,
    "chance_accuracy": 1.25,
    "ident_accuracy": 100.0,
    "ident_avg_target_sim": 0.999986201522991,
    "ident_avg_margin": 0.0004905067568750892,
    "gen_accuracy": 27.500000000000004,
    "gen_avg_target_sim": 0.9993174537741639,
    "gen_avg_margin": -0.00019100308824898936,
    "gen_avg_retrieved_human_similarity": 0.560444445,
    "gen_avg_human_similarity_regret": 0.24761110999999997,
    "gen_same_concept_accuracy": 42.5,
    "human_rdm_spearman": 0.37771650462440576,
    "exact_accuracy": 100.0,
    "clean_reextract_accuracy": 100.0,
    "exact_avg_target_sim": 1.0000000469376598,
    "clean_reextract_avg_target_sim": 1.0000000469376598
  },
  {
    "category": "fruits",
    "split_label": "fold_1",
    "split_seed": 1,
    "split_mode": "balanced_exemplar_folds",
    "model_name": "convnext_tiny",
    "pooling": "auto",
    "layer": "layer_3",
    "n_stored": 80,
    "n_probe": 40,
    "chance_accuracy": 1.25,
    "ident_accuracy": 100.0,
    "ident_avg_target_sim": 0.9894380596359282,
    "ident_avg_margin": 0.19704572406452076,
    "gen_accuracy": 50.0,
    "gen_avg_target_sim": 0.7456085379840813,
    "gen_avg_margin": -0.033903308870322384,
    "gen_avg_retrieved_human_similarity": 0.7108055550000001,
    "gen_avg_human_similarity_regret": 0.09725000000000002,
    "gen_same_concept_accuracy": 77.5,
    "human_rdm_spearman": 0.2977470615311246,
    "exact_accuracy": 100.0,
    "clean_reextract_accuracy": 100.0,
    "exact_avg_target_sim": 1.0000000260760329,
    "clean_reextract_avg_target_sim": 1.0000000260760329
  },
  {
    "category": "fruits",
    "split_label": "fold_2",
    "split_seed": 2,
    "split_mode": "balanced_exemplar_folds",
    "model_name": "convnext_tiny",
    "pooling": "auto",
    "layer": "layer_0",
    "n_stored": 80,
    "n_probe": 40,
    "chance_accuracy": 1.25,
    "ident_accuracy": 100.0,
    "ident_avg_target_sim": 0.9992440290540074,
    "ident_avg_margin": 0.0029890397035664956,
    "gen_accuracy": 17.5,
    "gen_avg_target_sim": 0.9912401776689432,
    "gen_avg_margin": -0.005306393111535454,
    "gen_avg_retrieved_human_similarity": 0.394944445,
    "gen_avg_human_similarity_regret": 0.41986111,
    "gen_same_concept_accuracy": 17.5,
    "human_rdm_spearman": 0.18964198467740265,
    "exact_accuracy": 100.0,
    "clean_reextract_accuracy": 100.0,
    "exact_avg_target_sim": 1.0000000357617889,
    "clean_reextract_avg_target_sim": 1.0000000357617889
  },
  {
    "category": "fruits",
    "split_label": "fold_2",
    "split_seed": 2,
    "split_mode": "balanced_exemplar_folds",
    "model_name": "convnext_tiny",
    "pooling": "auto",
    "layer": "layer_2",
    "n_stored": 80,
    "n_probe": 40,
    "chance_accuracy": 1.25,
    "ident_accuracy": 100.0,
    "ident_avg_target_sim": 0.9999871037881267,
    "ident_avg_margin": 0.0004771046631213929,
    "gen_accuracy": 25.0,
    "gen_avg_target_sim": 0.999237133525577,
    "gen_avg_margin": -0.00024409891816009054,
    "gen_avg_retrieved_human_similarity": 0.54938889,
    "gen_avg_human_similarity_regret": 0.26541666499999994,
    "gen_same_concept_accuracy": 37.5,
    "human_rdm_spearman": 0.37771650462440576,
    "exact_accuracy": 100.0,
    "clean_reextract_accuracy": 100.0,
    "exact_avg_target_sim": 1.0000000447024862,
    "clean_reextract_avg_target_sim": 1.0000000447024862
  },
  {
    "category": "fruits",
    "split_label": "fold_2",
    "split_seed": 2,
    "split_mode": "balanced_exemplar_folds",
    "model_name": "convnext_tiny",
    "pooling": "auto",
    "layer": "layer_3",
    "n_stored": 80,
    "n_probe": 40,
    "chance_accuracy": 1.25,
    "ident_accuracy": 100.0,
    "ident_avg_target_sim": 0.9898745041863307,
    "ident_avg_margin": 0.19448654393607187,
    "gen_accuracy": 45.0,
    "gen_avg_target_sim": 0.7707441839701016,
    "gen_avg_margin": -0.0180599359600384,
    "gen_avg_retrieved_human_similarity": 0.6830555549999999,
    "gen_avg_human_similarity_regret": 0.13174999999999998,
    "gen_same_concept_accuracy": 80.0,
    "human_rdm_spearman": 0.2977470615311246,
    "exact_accuracy": 100.0,
    "clean_reextract_accuracy": 100.0,
    "exact_avg_target_sim": 1.0000000283112072,
    "clean_reextract_avg_target_sim": 1.0000000283112072
  }
]