[
  {
    "category": "fruits",
    "split_label": "fold_0",
    "split_seed": 0,
    "split_mode": "balanced_exemplar_folds",
    "model_name": "vit_base_patch16_224",
    "pooling": "cls",
    "layer": "layer_0",
    "n_stored": 80,
    "n_probe": 40,
    "chance_accuracy": 1.25,
    "corruption_mode": "noise_shift_occlusion",
    "corruption_label": "noise5_shift2_occ0.5_dnoise0.01",
    "noise_std": 5.0,
    "max_shift": 2,
    "occlusion_frac": 0.5,
    "mask_frac": 0.3,
    "n_chunks": 6,
    "affine_strength": 0.05,
    "decision_noise_std": 0.01,
    "ident_accuracy": 0.0,
    "ident_avg_target_sim": 0.9997479692101479,
    "ident_avg_margin": -0.00015793293714523317,
    "gen_accuracy": 0.0,
    "gen_avg_target_sim": 0.9996972516179085,
    "gen_avg_margin": -0.00024019479751586915,
    "gen_avg_retrieved_human_similarity": 0.21275000000000005,
    "gen_avg_human_similarity_regret": 0.58675,
    "gen_same_concept_accuracy": 0.0,
    "human_rdm_spearman": 0.127104567410225,
    "exact_accuracy": 100.0,
    "clean_reextract_accuracy": 100.0,
    "exact_avg_target_sim": 1.000000035762787,
    "clean_reextract_avg_target_sim": 1.000000035762787
  },
  {
    "category": "fruits",
    "split_label": "fold_0",
    "split_seed": 0,
    "split_mode": "balanced_exemplar_folds",
    "model_name": "vit_base_patch16_224",
    "pooling": "cls",
    "layer": "layer_11",
    "n_stored": 80,
    "n_probe": 40,
    "chance_accuracy": 1.25,
    "corruption_mode": "noise_shift_occlusion",
    "corruption_label": "noise5_shift2_occ0.5_dnoise0.01",
    "noise_std": 5.0,
    "max_shift": 2,
    "occlusion_frac": 0.5,
    "mask_frac": 0.3,
    "n_chunks": 6,
    "affine_strength": 0.05,
    "decision_noise_std": 0.01,
    "ident_accuracy": 65.0,
    "ident_avg_target_sim": 0.9379167154431343,
    "ident_avg_margin": 0.012258058786392212,
    "gen_accuracy": 37.5,
    "gen_avg_target_sim": 0.9236816197633744,
    "gen_avg_margin": -0.0136148601770401,
    "gen_avg_retrieved_human_similarity": 0.6575,
    "gen_avg_human_similarity_regret": 0.142,
    "gen_same_concept_accuracy": 70.0,
    "human_rdm_spearman": 0.26378508251273497,
    "exact_accuracy": 100.0,
    "clean_reextract_accuracy": 100.0,
    "exact_avg_target_sim": 1.000000038743019,
    "clean_reextract_avg_target_sim": 1.000000038743019
  },
  {
    "category": "fruits",
    "split_label": "fold_0",
    "split_seed": 0,
    "split_mode": "balanced_exemplar_folds",
    "model_name": "vit_base_patch16_224",
    "pooling": "cls",
    "layer": "layer_6",
    "n_stored": 80,
    "n_probe": 40,
    "chance_accuracy": 1.25,
    "corruption_mode": "noise_shift_occlusion",
    "corruption_label": "noise5_shift2_occ0.5_dnoise0.01",
    "noise_std": 5.0,
    "max_shift": 2,
    "occlusion_frac": 0.5,
    "mask_frac": 0.3,
    "n_chunks": 6,
    "affine_strength": 0.05,
    "decision_noise_std": 0.01,
    "ident_accuracy": 52.5,
    "ident_avg_target_sim": 0.971586312353611,
    "ident_avg_margin": 0.010636299848556519,
    "gen_accuracy": 7.5,
    "gen_avg_target_sim": 0.9503110885620117,
    "gen_avg_margin": -0.019156414270401,
    "gen_avg_retrieved_human_similarity": 0.3375,
    "gen_avg_human_similarity_regret": 0.462,
    "gen_same_concept_accuracy": 7.5,
    "human_rdm_spearman": 0.2978042848406152,
    "exact_accuracy": 100.0,
    "clean_reextract_accuracy": 100.0,
    "exact_avg_target_sim": 1.000000035762787,
    "clean_reextract_avg_target_sim": 1.000000035762787
  },
  {
    "category": "fruits",
    "split_label": "fold_1",
    "split_seed": 1,
    "split_mode": "balanced_exemplar_folds",
    "model_name": "vit_base_patch16_224",
    "pooling": "cls",
    "layer": "layer_0",
    "n_stored": 80,
    "n_probe": 40,
    "chance_accuracy": 1.25,
    "corruption_mode": "noise_shift_occlusion",
    "corruption_label": "noise5_shift2_occ0.5_dnoise0.01",
    "noise_std": 5.0,
    "max_shift": 2,
    "occlusion_frac": 0.5,
    "mask_frac": 0.3,
    "n_chunks": 6,
    "affine_strength": 0.05,
    "decision_noise_std": 0.01,
    "ident_accuracy": 2.5,
    "ident_avg_target_sim": 0.9997359082102776,
    "ident_avg_margin": -0.00016028806567192078,
    "gen_accuracy": 0.0,
    "gen_avg_target_sim": 0.9996753171086311,
    "gen_avg_margin": -0.00026502609252929685,
    "gen_avg_retrieved_human_similarity": 0.17675000000000002,
    "gen_avg_human_similarity_regret": 0.631305555,
    "gen_same_concept_accuracy": 0.0,
    "human_rdm_spearman": 0.127104567410225,
    "exact_accuracy": 100.0,
    "clean_reextract_accuracy": 100.0,
    "exact_avg_target_sim": 1.0000000402331353,
    "clean_reextract_avg_target_sim": 1.0000000402331353
  },
  {
    "category": "fruits",
    "split_label": "fold_1",
    "split_seed": 1,
    "split_mode": "balanced_exemplar_folds",
    "model_name": "vit_base_patch16_224",
    "pooling": "cls",
    "layer": "layer_11",
    "n_stored": 80,
    "n_probe": 40,
    "chance_accuracy": 1.25,
    "corruption_mode": "noise_shift_occlusion",
    "corruption_label": "noise5_shift2_occ0.5_dnoise0.01",
    "noise_std": 5.0,
    "max_shift": 2,
    "occlusion_frac": 0.5,
    "mask_frac": 0.3,
    "n_chunks": 6,
    "affine_strength": 0.05,
    "decision_noise_std": 0.01,
    "ident_accuracy": 57.49999999999999,
    "ident_avg_target_sim": 0.9368479579687119,
    "ident_avg_margin": 0.010378997772932053,
    "gen_accuracy": 40.0,
    "gen_avg_target_sim": 0.9302724480628968,
    "gen_avg_margin": -0.008244463801383972,
    "gen_avg_retrieved_human_similarity": 0.6765000000000001,
    "gen_avg_human_similarity_regret": 0.131555555,
    "gen_same_concept_accuracy": 72.5,
    "human_rdm_spearman": 0.26378508251273497,
    "exact_accuracy": 100.0,
    "clean_reextract_accuracy": 100.0,
    "exact_avg_target_sim": 1.0000000536441802,
    "clean_reextract_avg_target_sim": 1.0000000536441802
  },
  {
    "category": "fruits",
    "split_label": "fold_1",
    "split_seed": 1,
    "split_mode": "balanced_exemplar_folds",
    "model_name": "vit_base_patch16_224",
    "pooling": "cls",
    "layer": "layer_6",
    "n_stored": 80,
    "n_probe": 40,
    "chance_accuracy": 1.25,
    "corruption_mode": "noise_shift_occlusion",
    "corruption_label": "noise5_shift2_occ0.5_dnoise0.01",
    "noise_std": 5.0,
    "max_shift": 2,
    "occlusion_frac": 0.5,
    "mask_frac": 0.3,
    "n_chunks": 6,
    "affine_strength": 0.05,
    "decision_noise_std": 0.01,
    "ident_accuracy": 51.24999999999999,
    "ident_avg_target_sim": 0.9723785601556301,
    "ident_avg_margin": 0.009838566184043884,
    "gen_accuracy": 7.5,
    "gen_avg_target_sim": 0.9546685114502906,
    "gen_avg_margin": -0.012921682000160218,
    "gen_avg_retrieved_human_similarity": 0.32975,
    "gen_avg_human_similarity_regret": 0.47830555500000005,
    "gen_same_concept_accuracy": 10.0,
    "human_rdm_spearman": 0.2978042848406152,
    "exact_accuracy": 100.0,
    "clean_reextract_accuracy": 100.0,
    "exact_avg_target_sim": 1.0000000283122064,
    "clean_reextract_avg_target_sim": 1.0000000283122064
  },
  {
    "category": "fruits",
    "split_label": "fold_2",
    "split_seed": 2,
    "split_mode": "balanced_exemplar_folds",
    "model_name": "vit_base_patch16_224",
    "pooling": "cls",
    "layer": "layer_0",
    "n_stored": 80,
    "n_probe": 40,
    "chance_accuracy": 1.25,
    "corruption_mode": "noise_shift_occlusion",
    "corruption_label": "noise5_shift2_occ0.5_dnoise0.01",
    "noise_std": 5.0,
    "max_shift": 2,
    "occlusion_frac": 0.5,
    "mask_frac": 0.3,
    "n_chunks": 6,
    "affine_strength": 0.05,
    "decision_noise_std": 0.01,
    "ident_accuracy": 2.5,
    "ident_avg_target_sim": 0.9997304305434227,
    "ident_avg_margin": -0.00015917122364044188,
    "gen_accuracy": 2.5,
    "gen_avg_target_sim": 0.9996260300278663,
    "gen_avg_margin": -0.00031405538320541384,
    "gen_avg_retrieved_human_similarity": 0.22769444500000002,
    "gen_avg_human_similarity_regret": 0.58711111,
    "gen_same_concept_accuracy": 5.0,
    "human_rdm_spearman": 0.127104567410225,
    "exact_accuracy": 100.0,
    "clean_reextract_accuracy": 100.0,
    "exact_avg_target_sim": 1.0000000402331353,
    "clean_reextract_avg_target_sim": 1.0000000402331353
  },
  {
    "category": "fruits",
    "split_label": "fold_2",
    "split_seed": 2,
    "split_mode": "balanced_exemplar_folds",
    "model_name": "vit_base_patch16_224",
    "pooling": "cls",
    "layer": "layer_11",
    "n_stored": 80,
    "n_probe": 40,
    "chance_accuracy": 1.25,
    "corruption_mode": "noise_shift_occlusion",
    "corruption_label": "noise5_shift2_occ0.5_dnoise0.01",
    "noise_std": 5.0,
    "max_shift": 2,
    "occlusion_frac": 0.5,
    "mask_frac": 0.3,
    "n_chunks": 6,
    "affine_strength": 0.05,
    "decision_noise_std": 0.01,
    "ident_accuracy": 57.49999999999999,
    "ident_avg_target_sim": 0.9350377395749092,
    "ident_avg_margin": 0.009226598590612412,
    "gen_accuracy": 55.00000000000001,
    "gen_avg_target_sim": 0.9326473921537399,
    "gen_avg_margin": -0.008146040141582489,
    "gen_avg_retrieved_human_similarity": 0.7195,
    "gen_avg_human_similarity_regret": 0.095305555,
    "gen_same_concept_accuracy": 80.0,
    "human_rdm_spearman": 0.26378508251273497,
    "exact_accuracy": 100.0,
    "clean_reextract_accuracy": 100.0,
    "exact_avg_target_sim": 1.0000000476837159,
    "clean_reextract_avg_target_sim": 1.0000000476837159
  },
  {
    "category": "fruits",
    "split_label": "fold_2",
    "split_seed": 2,
    "split_mode": "balanced_exemplar_folds",
    "model_name": "vit_base_patch16_224",
    "pooling": "cls",
    "layer": "layer_6",
    "n_stored": 80,
    "n_probe": 40,
    "chance_accuracy": 1.25,
    "corruption_mode": "noise_shift_occlusion",
    "corruption_label": "noise5_shift2_occ0.5_dnoise0.01",
    "noise_std": 5.0,
    "max_shift": 2,
    "occlusion_frac": 0.5,
    "mask_frac": 0.3,
    "n_chunks": 6,
    "affine_strength": 0.05,
    "decision_noise_std": 0.01,
    "ident_accuracy": 53.75,
    "ident_avg_target_sim": 0.9723240904510021,
    "ident_avg_margin": 0.011150563508272171,
    "gen_accuracy": 5.0,
    "gen_avg_target_sim": 0.9500869572162628,
    "gen_avg_margin": -0.019125400483608244,
    "gen_avg_retrieved_human_similarity": 0.3135,
    "gen_avg_human_similarity_regret": 0.5013055550000001,
    "gen_same_concept_accuracy": 7.5,
    "human_rdm_spearman": 0.2978042848406152,
    "exact_accuracy": 100.0,
    "clean_reextract_accuracy": 100.0,
    "exact_avg_target_sim": 1.0000000402331353,
    "clean_reextract_avg_target_sim": 1.0000000402331353
  }
]